pytest_httpx_recorder/__init__.py
pytest_httpx_recorder/config/__init__.py
pytest_httpx_recorder/config/meta.py
pytest_httpx_recorder/recorder/__init__.py
pytest_httpx_recorder/recorder/base.py
pytest_httpx_recorder/recorder/recorder.py
pytest_httpx_recorder/recorder/set.py
pytest_httpx_recorder-0.0.1.dist-info/LICENSE
pytest_httpx_recorder-0.0.1.dist-info/METADATA
pytest_httpx_recorder-0.0.1.dist-info/WHEEL
pytest_httpx_recorder-0.0.1.dist-info/top_level.txt
pytest_httpx_recorder-0.0.1.dist-info/RECORD
